holobio/Main_.py
holobio/__init__.py
holobio/__main__.py
holobio/functions_GUI.py
holobio/main_DHM_PP.py
holobio/main_DHM_RT.py
holobio/main_DLHM_PP.py
holobio/main_DLHM_RT.py
holobio/parallel_rc.py
holobio/phaseShifting.py
holobio/pyDHM_methods.py
holobio/settings.py
holobio/settingsCompensation.py
holobio/tools_GUI.py
holobio/tools_microstructure.py
holobio/track_particles_kalman.py
holobio/unwrap_methods.py
holobio/unwrapping.py
holobio/utilities.py
holobio-1.0.2.dist-info/licenses/LICENSE
holobio-1.0.2.dist-info/METADATA
holobio-1.0.2.dist-info/WHEEL
holobio-1.0.2.dist-info/entry_points.txt
holobio-1.0.2.dist-info/top_level.txt
holobio-1.0.2.dist-info/RECORD
