Metadata-Version: 2.4
Name: holoBio
Version: 1.0.2
Summary: A comprehensive library for Digital Holographic Microscopy (DHM)
Author-email: SOPHIA-Research-Lab <racastaneq@eafit.edu.co>
License: GPL-3.0
Project-URL: Homepage, https://github.com/SOPHIA-Research-Lab/HoloBio
Project-URL: Repository, https://github.com/SOPHIA-Research-Lab/HoloBio
Classifier: Development Status :: 5 - Production/Stable
Classifier: Intended Audience :: Science/Research
Classifier: Programming Language :: Python :: 3
Classifier: License :: OSI Approved :: GNU General Public License v3 (GPLv3)
Classifier: Operating System :: OS Independent
License-File: LICENSE
Requires-Dist: numpy
Requires-Dist: Pillow
Requires-Dist: matplotlib
Requires-Dist: imageio
Requires-Dist: scikit-image
Requires-Dist: scipy
Requires-Dist: opencv-python
Requires-Dist: pandas
Requires-Dist: customtkinter
Requires-Dist: pandastable
Dynamic: license-file
